james/__init__.py
james/azure.py
james/cli.py
james/config.py
james/james.py
james/platform.py
james/review.py
james/utils.py
dsl_james-0.1.4.dist-info/AUTHORS.rst
dsl_james-0.1.4.dist-info/LICENSE.txt
dsl_james-0.1.4.dist-info/METADATA
dsl_james-0.1.4.dist-info/WHEEL
dsl_james-0.1.4.dist-info/entry_points.txt
dsl_james-0.1.4.dist-info/top_level.txt
dsl_james-0.1.4.dist-info/RECORD
