Metadata-Version: 2.1
Name: dsl-james
Version: 0.1.4
Summary: CLI tool for starting up a project
Home-page: https://github.com/data-science-lab-amsterdam/james
Author: Robert van Straalen
Author-email: robert.vanstraalen@datasciencelab.nl
License: UNKNOWN
Keywords: project,startup,cookiecutter,MLOps,cli,code inspection
Platform: UNKNOWN
Classifier: Development Status :: 3 - Alpha
Classifier: Intended Audience :: Developers
Classifier: Natural Language :: English
Classifier: Programming Language :: Python :: 3
Classifier: Programming Language :: Python :: 3.6
Classifier: Programming Language :: Python :: 3.7
Classifier: Programming Language :: Python :: 3.8
Classifier: Programming Language :: Python :: 3.9
Requires-Python: >=3.6
Requires-Dist: Click (>=7.0)
Requires-Dist: loguru
Requires-Dist: flake8
Requires-Dist: flake8-docstrings
Requires-Dist: mypy
Requires-Dist: cookiecutter
Requires-Dist: termcolor
